topsis_deepanshi/401903006.py
topsis_deepanshi_401903006-1.0.0.dist-info/LICENSE.txt
topsis_deepanshi_401903006-1.0.0.dist-info/METADATA
topsis_deepanshi_401903006-1.0.0.dist-info/WHEEL
topsis_deepanshi_401903006-1.0.0.dist-info/entry_points.txt
topsis_deepanshi_401903006-1.0.0.dist-info/top_level.txt
topsis_deepanshi_401903006-1.0.0.dist-info/RECORD
